{"type":"Sprite","props":{"x":0,"y":0,"texture":"Sprites/Car2.png","name":"Car_01","width":136,"height":248,"pivotX":68,"pivotY":124,"presetID":1,"isPresetRoot":true},"compId":154,"child":[{"type":"Script","props":{"y":7,"x":14,"width":107,"label":"Car","isSensor":true,"height":232,"presetID":2,"runtime":"Laya.BoxCollider"},"compId":77},{"type":"Script","props":{"type":"kinematic","allowSleep":false,"presetID":3,"runtime":"Laya.RigidBody"},"compId":78},{"type":"Script","props":{"presetID":4,"runtime":"Car.ts"},"compId":79}],"loadList":["Sprites/Car2.png"],"loadList3D":[]}